[
    {
        "firstName": "Collett",
        "lastName": "Heenan",
        "title": "Administrative Assistant for College of Arts & Sciences",
        "avatarURL": "https://fhu.edu/wp-content/uploads/collett-heenan-updated.jpg",
        "dateAdded": "11/06/2025"
    },
    {
        "firstName": "John",
        "lastName": "McLaughlin",
        "title": "Professor of English",
        "avatarURL": "https://fhu.edu/wp-content/uploads/john-mclaughlin-updated.jpg",
        "dateAdded": "11/06/2025"
    }
]